{
    "-1": "Outlier: General Product Troubleshooting",
    "0": "Intermittent Software and Maintenance Updates",
    "1": "Network Connectivity and Setup Troubleshooting",
    "2": "Account Access and Password Recovery",
    "3": "Data Loss and Urgent File Recovery",
    "4": "Software Bug Reporting and Fix Verification",
    "5": "UI Error Messages and Screen Pop-ups",
    "6": "Purchase Logistics and ID/Address Inquiries",
    "7": "Data Security and Privacy Safety",
    "8": "Battery Charging and Power Supply Issues",
    "9": "Hardware Display and Screen Flickering",
    "10": "Critical Power Failure",
    "11": "Acoustic Hardware Anomalies and Strange Noises",
    "12": "System Glitches and Software Freezing"
}